malpzsim/__init__.py
malpzsim/agents/keyboard_input.py
malpzsim/agents/searchers.py
malpzsim/sims/mal_petting_zoo_simulator.py
malpzsim/wrappers/gym_wrapper.py
malpzsim/wrappers/wrapper.py
mal_petting_zoo_simulator-0.0.21.dist-info/AUTHORS
mal_petting_zoo_simulator-0.0.21.dist-info/LICENSE
mal_petting_zoo_simulator-0.0.21.dist-info/METADATA
mal_petting_zoo_simulator-0.0.21.dist-info/WHEEL
mal_petting_zoo_simulator-0.0.21.dist-info/top_level.txt
mal_petting_zoo_simulator-0.0.21.dist-info/RECORD
